{
  "data": {
    "article": {},
    "attachments": {},
    "author_id": "1564990471327215619",
    "conversation_id": "2063196008809394546",
    "created_at": "2026-06-06T09:50:02.000Z",
    "edit_controls": {
      "editable_until": "2026-06-06T10:50:02.000Z",
      "edits_remaining": 5,
      "is_edit_eligible": false
    },
    "edit_history_tweet_ids": [
      "2063196708604088577"
    ],
    "entities": {
      "mentions": [
        {
          "end": 12,
          "id": "1409516495571501066",
          "start": 0,
          "username": "DrankghostU"
        }
      ]
    },
    "geo": {},
    "id": "2063196708604088577",
    "in_reply_to_user_id": "1409516495571501066",
    "lang": "zh",
    "note_tweet": {
      "entities": {}
    },
    "possibly_sensitive": false,
    "public_metrics": {
      "bookmark_count": 0,
      "impression_count": 0,
      "like_count": 0,
      "quote_count": 0,
      "reply_count": 0,
      "retweet_count": 0
    },
    "referenced_tweets": [
      {
        "id": "2063196008809394546",
        "type": "replied_to"
      }
    ],
    "reply_settings": "everyone",
    "text": "@DrankghostU 老婆我给你发私信了！！！"
  },
  "includes": {
    "tweets": [
      {
        "article": {},
        "attachments": {},
        "author_id": "1564990471327215619",
        "conversation_id": "2063196008809394546",
        "created_at": "2026-06-06T09:50:02.000Z",
        "edit_controls": {
          "editable_until": "2026-06-06T10:50:02.000Z",
          "edits_remaining": 5,
          "is_edit_eligible": false
        },
        "edit_history_tweet_ids": [
          "2063196708604088577"
        ],
        "entities": {
          "mentions": [
            {
              "end": 12,
              "id": "1409516495571501066",
              "start": 0,
              "username": "DrankghostU"
            }
          ]
        },
        "geo": {},
        "id": "2063196708604088577",
        "in_reply_to_user_id": "1409516495571501066",
        "lang": "zh",
        "note_tweet": {
          "entities": {}
        },
        "possibly_sensitive": false,
        "public_metrics": {
          "bookmark_count": 0,
          "impression_count": 0,
          "like_count": 0,
          "quote_count": 0,
          "reply_count": 0,
          "retweet_count": 0
        },
        "referenced_tweets": [
          {
            "id": "2063196008809394546",
            "type": "replied_to"
          }
        ],
        "reply_settings": "everyone",
        "text": "@DrankghostU 老婆我给你发私信了！！！"
      },
      {
        "article": {},
        "attachments": {},
        "author_id": "1409516495571501066",
        "conversation_id": "2063196008809394546",
        "created_at": "2026-06-06T09:47:15.000Z",
        "edit_controls": {
          "editable_until": "2026-06-06T10:47:15.000Z",
          "edits_remaining": 5,
          "is_edit_eligible": true
        },
        "edit_history_tweet_ids": [
          "2063196008809394546"
        ],
        "entities": {
          "urls": [
            {
              "display_url": "x.com/bisco91395061/…",
              "end": 61,
              "expanded_url": "https://twitter.com/bisco91395061/status/2063191796797292872",
              "start": 38,
              "url": "https://t.co/eNFljDOgAd"
            }
          ]
        },
        "geo": {},
        "id": "2063196008809394546",
        "lang": "zh",
        "note_tweet": {
          "entities": {}
        },
        "possibly_sensitive": false,
        "public_metrics": {
          "bookmark_count": 0,
          "impression_count": 9,
          "like_count": 1,
          "quote_count": 0,
          "reply_count": 1,
          "retweet_count": 0
        },
        "referenced_tweets": [
          {
            "id": "2063191796797292872",
            "type": "quoted"
          }
        ],
        "reply_settings": "everyone",
        "text": "我草我怎么才看到？！？！？？咋这么萌？！？！？？？？我草我爱这个菜菜警官。 https://t.co/eNFljDOgAd"
      }
    ],
    "users": [
      {
        "created_at": "2022-08-31T14:56:34.000Z",
        "description": "＝菜菜｜od自傷｜傻福精神病休學中｜LGBTQ🏳️‍🌈友好｜競馬🐎｜同类互fo❤️大欢迎｜生理心理女 别再问了｜直fo是喜欢泥🤲❤️",
        "id": "1564990471327215619",
        "location": "🚪52/188",
        "name": "菜菜警官",
        "pinned_tweet_id": "2050266190665388506",
        "profile_image_url": "https://pbs.twimg.com/profile_images/2047006666068307968/ZVRv_hZa_normal.jpg",
        "protected": false,
        "public_metrics": {
          "followers_count": 448,
          "following_count": 179,
          "like_count": 7228,
          "listed_count": 1,
          "media_count": 82,
          "tweet_count": 970
        },
        "username": "bisco91395061",
        "verified": false
      },
      {
        "created_at": "2021-06-28T14:18:23.000Z",
        "description": "𓆩♡𓆪 死目莉 𓆩♡𓆪\n🩹 | 双相情感障碍 • 𝖠𝖣𝖧𝖣 • 重焦 • 💊🔪🩸\n\n🎀没有喜欢死目莉的觉悟就不要靠近死目莉。\n💕女宝互关熟了可以恰v \n🫧男性推油请给恶魔死目莉的熔炼炉投入52cny喵😤",
        "id": "1409516495571501066",
        "location": "我想要的是世界上根本就没有的东西",
        "name": "早乙女死目莉2.0",
        "pinned_tweet_id": "2063162560157720985",
        "profile_image_url": "https://pbs.twimg.com/profile_images/2063196138987995136/5SVYRVyv_normal.jpg",
        "protected": false,
        "public_metrics": {
          "followers_count": 340,
          "following_count": 186,
          "like_count": 84,
          "listed_count": 1,
          "media_count": 38,
          "tweet_count": 450
        },
        "username": "DrankghostU",
        "verified": false
      }
    ]
  }
}