{
  "data": {
    "article": {},
    "attachments": {},
    "author_id": "1564990471327215619",
    "conversation_id": "2066089105872867577",
    "created_at": "2026-06-14T12:39:13.000Z",
    "edit_controls": {
      "editable_until": "2026-06-14T13:39:13.000Z",
      "edits_remaining": 5,
      "is_edit_eligible": false
    },
    "edit_history_tweet_ids": [
      "2066138389863334045"
    ],
    "entities": {
      "mentions": [
        {
          "end": 13,
          "id": "1966505502919270400",
          "start": 0,
          "username": "QiShuiBuXing"
        }
      ]
    },
    "geo": {},
    "id": "2066138389863334045",
    "in_reply_to_user_id": "1966505502919270400",
    "lang": "ja",
    "note_tweet": {
      "entities": {}
    },
    "possibly_sensitive": false,
    "public_metrics": {
      "bookmark_count": 0,
      "impression_count": 0,
      "like_count": 0,
      "quote_count": 0,
      "reply_count": 0,
      "retweet_count": 0
    },
    "referenced_tweets": [
      {
        "id": "2066125297142108229",
        "type": "replied_to"
      }
    ],
    "reply_settings": "everyone",
    "text": "@QiShuiBuXing 笑死了啊啊啊精品大果"
  },
  "includes": {
    "tweets": [
      {
        "article": {},
        "attachments": {},
        "author_id": "1564990471327215619",
        "conversation_id": "2066089105872867577",
        "created_at": "2026-06-14T12:39:13.000Z",
        "edit_controls": {
          "editable_until": "2026-06-14T13:39:13.000Z",
          "edits_remaining": 5,
          "is_edit_eligible": false
        },
        "edit_history_tweet_ids": [
          "2066138389863334045"
        ],
        "entities": {
          "mentions": [
            {
              "end": 13,
              "id": "1966505502919270400",
              "start": 0,
              "username": "QiShuiBuXing"
            }
          ]
        },
        "geo": {},
        "id": "2066138389863334045",
        "in_reply_to_user_id": "1966505502919270400",
        "lang": "ja",
        "note_tweet": {
          "entities": {}
        },
        "possibly_sensitive": false,
        "public_metrics": {
          "bookmark_count": 0,
          "impression_count": 0,
          "like_count": 0,
          "quote_count": 0,
          "reply_count": 0,
          "retweet_count": 0
        },
        "referenced_tweets": [
          {
            "id": "2066125297142108229",
            "type": "replied_to"
          }
        ],
        "reply_settings": "everyone",
        "text": "@QiShuiBuXing 笑死了啊啊啊精品大果"
      },
      {
        "article": {},
        "attachments": {},
        "author_id": "1966505502919270400",
        "conversation_id": "2066089105872867577",
        "created_at": "2026-06-14T11:47:12.000Z",
        "edit_controls": {
          "editable_until": "2026-06-14T12:47:12.000Z",
          "edits_remaining": 5,
          "is_edit_eligible": false
        },
        "edit_history_tweet_ids": [
          "2066125297142108229"
        ],
        "entities": {
          "mentions": [
            {
              "end": 14,
              "id": "1564990471327215619",
              "start": 0,
              "username": "bisco91395061"
            }
          ]
        },
        "geo": {},
        "id": "2066125297142108229",
        "in_reply_to_user_id": "1564990471327215619",
        "lang": "ja",
        "note_tweet": {
          "entities": {}
        },
        "possibly_sensitive": false,
        "public_metrics": {
          "bookmark_count": 0,
          "impression_count": 56,
          "like_count": 0,
          "quote_count": 0,
          "reply_count": 1,
          "retweet_count": 0
        },
        "referenced_tweets": [
          {
            "id": "2066089105872867577",
            "type": "replied_to"
          }
        ],
        "reply_settings": "everyone",
        "text": "@bisco91395061 已经有槟榔版了"
      }
    ],
    "users": [
      {
        "created_at": "2022-08-31T14:56:34.000Z",
        "description": "＝菜菜｜od自傷｜傻福精神病休學中｜LGBTQ🏳️‍🌈友好｜競馬🐎｜同类互fo❤️大欢迎｜生理心理女 别再问了｜直fo是喜欢泥🤲❤️",
        "id": "1564990471327215619",
        "location": "🚪52/188",
        "name": "菜菜警官",
        "pinned_tweet_id": "2050266190665388506",
        "profile_image_url": "https://pbs.twimg.com/profile_images/2047006666068307968/ZVRv_hZa_normal.jpg",
        "protected": false,
        "public_metrics": {
          "followers_count": 638,
          "following_count": 249,
          "like_count": 7882,
          "listed_count": 1,
          "media_count": 96,
          "tweet_count": 1297
        },
        "username": "bisco91395061",
        "verified": false
      },
      {
        "created_at": "2025-09-12T14:13:54.000Z",
        "description": "遇到真爱的喜悦，失去至亲的痛苦，都是化学层面的问题。无非是内啡肽、荷尔蒙、多巴胺以及一系列激素的共同作用，本质上是一群化合物操弄着你的感受。",
        "id": "1966505502919270400",
        "name": "百忧解",
        "pinned_tweet_id": "2020841917156901347",
        "profile_image_url": "https://pbs.twimg.com/profile_images/1987177220130119680/y9K2ZMnS_normal.jpg",
        "protected": false,
        "public_metrics": {
          "followers_count": 56,
          "following_count": 1577,
          "like_count": 12,
          "listed_count": 0,
          "media_count": 30,
          "tweet_count": 64
        },
        "username": "QiShuiBuXing",
        "verified": false
      }
    ]
  }
}