{
  "data": {
    "article": {},
    "attachments": {},
    "author_id": "1564990471327215619",
    "conversation_id": "2065746595170419092",
    "created_at": "2026-06-13T11:53:06.000Z",
    "edit_controls": {
      "editable_until": "2026-06-13T12:53:06.000Z",
      "edits_remaining": 5,
      "is_edit_eligible": false
    },
    "edit_history_tweet_ids": [
      "2065764396924858621"
    ],
    "entities": {
      "mentions": [
        {
          "end": 14,
          "id": "1639996371879985157",
          "start": 0,
          "username": "SupernovaLLan"
        }
      ]
    },
    "geo": {},
    "id": "2065764396924858621",
    "in_reply_to_user_id": "1639996371879985157",
    "lang": "ja",
    "note_tweet": {
      "entities": {}
    },
    "possibly_sensitive": false,
    "public_metrics": {
      "bookmark_count": 0,
      "impression_count": 0,
      "like_count": 0,
      "quote_count": 0,
      "reply_count": 0,
      "retweet_count": 0
    },
    "referenced_tweets": [
      {
        "id": "2065746595170419092",
        "type": "replied_to"
      }
    ],
    "reply_settings": "everyone",
    "text": "@SupernovaLLan 🤤🤤🤤🤤美味啊"
  },
  "includes": {
    "media": [
      {
        "height": 2048,
        "media_key": "3_2065746583505993728",
        "public_metrics": {},
        "type": "photo",
        "url": "https://pbs.twimg.com/media/HKsBkqnaAAAltaB.jpg",
        "width": 1536
      }
    ],
    "tweets": [
      {
        "article": {},
        "attachments": {},
        "author_id": "1564990471327215619",
        "conversation_id": "2065746595170419092",
        "created_at": "2026-06-13T11:53:06.000Z",
        "edit_controls": {
          "editable_until": "2026-06-13T12:53:06.000Z",
          "edits_remaining": 5,
          "is_edit_eligible": false
        },
        "edit_history_tweet_ids": [
          "2065764396924858621"
        ],
        "entities": {
          "mentions": [
            {
              "end": 14,
              "id": "1639996371879985157",
              "start": 0,
              "username": "SupernovaLLan"
            }
          ]
        },
        "geo": {},
        "id": "2065764396924858621",
        "in_reply_to_user_id": "1639996371879985157",
        "lang": "ja",
        "note_tweet": {
          "entities": {}
        },
        "possibly_sensitive": false,
        "public_metrics": {
          "bookmark_count": 0,
          "impression_count": 0,
          "like_count": 0,
          "quote_count": 0,
          "reply_count": 0,
          "retweet_count": 0
        },
        "referenced_tweets": [
          {
            "id": "2065746595170419092",
            "type": "replied_to"
          }
        ],
        "reply_settings": "everyone",
        "text": "@SupernovaLLan 🤤🤤🤤🤤美味啊"
      },
      {
        "article": {},
        "attachments": {
          "media_keys": [
            "3_2065746583505993728"
          ]
        },
        "author_id": "1639996371879985157",
        "context_annotations": [
          {
            "domain": {
              "description": "Categories within Brand Verticals that narrow down the scope of Brands",
              "id": "46",
              "name": "Business Taxonomy"
            },
            "entity": {
              "description": "Brands, companies, advertisers and every non-person handle with the profit intent and related to foods & beverages such as snacks, soft drinks, beers.",
              "id": "1557696888568045569",
              "name": "Food & Beverage Business"
            }
          }
        ],
        "conversation_id": "2065746595170419092",
        "created_at": "2026-06-13T10:42:22.000Z",
        "edit_controls": {
          "editable_until": "2026-06-13T11:42:22.000Z",
          "edits_remaining": 5,
          "is_edit_eligible": true
        },
        "edit_history_tweet_ids": [
          "2065746595170419092"
        ],
        "entities": {
          "urls": [
            {
              "display_url": "pic.x.com/7hGRcmZihl",
              "end": 30,
              "expanded_url": "https://x.com/SupernovaLLan/status/2065746595170419092/photo/1",
              "media_key": "3_2065746583505993728",
              "start": 7,
              "url": "https://t.co/7hGRcmZihl"
            }
          ]
        },
        "geo": {},
        "id": "2065746595170419092",
        "lang": "zh",
        "note_tweet": {
          "entities": {}
        },
        "possibly_sensitive": true,
        "public_metrics": {
          "bookmark_count": 0,
          "impression_count": 27,
          "like_count": 5,
          "quote_count": 0,
          "reply_count": 1,
          "retweet_count": 0
        },
        "reply_settings": "everyone",
        "text": "冷面怎么说🤤 https://t.co/7hGRcmZihl"
      }
    ],
    "users": [
      {
        "created_at": "2022-08-31T14:56:34.000Z",
        "description": "＝菜菜｜od自傷｜傻福精神病休學中｜LGBTQ🏳️‍🌈友好｜競馬🐎｜同类互fo❤️大欢迎｜生理心理女 别再问了｜直fo是喜欢泥🤲❤️｜骂我先骂@cryptochenrui",
        "entities": {
          "description": {
            "mentions": [
              {
                "end": 85,
                "start": 71,
                "username": "cryptochenrui"
              }
            ]
          }
        },
        "id": "1564990471327215619",
        "location": "🚪52/188",
        "name": "菜菜警官",
        "pinned_tweet_id": "2065026751257100409",
        "profile_image_url": "https://pbs.twimg.com/profile_images/2047006666068307968/ZVRv_hZa_normal.jpg",
        "protected": false,
        "public_metrics": {
          "followers_count": 621,
          "following_count": 236,
          "like_count": 7750,
          "listed_count": 1,
          "media_count": 96,
          "tweet_count": 1213
        },
        "username": "bisco91395061",
        "verified": false
      },
      {
        "created_at": "2023-03-26T14:23:40.000Z",
        "description": "Per Aspera Ad Astra",
        "id": "1639996371879985157",
        "location": "Laniakea Supercluster ",
        "name": "*⁂汐渋鈴蘭⁂*.･ﾟﾟ",
        "pinned_tweet_id": "1835705937086333243",
        "profile_image_url": "https://pbs.twimg.com/profile_images/2053522922648776704/qB9xPTfk_normal.jpg",
        "protected": false,
        "public_metrics": {
          "followers_count": 388,
          "following_count": 606,
          "like_count": 26677,
          "listed_count": 2,
          "media_count": 1186,
          "tweet_count": 11062
        },
        "username": "SupernovaLLan",
        "verified": false
      }
    ]
  }
}